MANIFEST.in
analytic_contract_hr_expense_view.xml
setup.py
./__init__.py
./__openerp__.py
./analytic_contract_hr_expense.py
i18n/analytic_contract_hr_expense.pot
i18n/ar.po
i18n/cs.po
i18n/da.po
i18n/de.po
i18n/en_GB.po
i18n/es.po
i18n/fr.po
i18n/hr.po
i18n/hu.po
i18n/it.po
i18n/mk.po
i18n/mn.po
i18n/nb.po
i18n/nl.po
i18n/nl_BE.po
i18n/pl.po
i18n/pt.po
i18n/pt_BR.po
i18n/ro.po
i18n/sl.po
i18n/tr.po
i18n/zh_CN.po
openerp_analytic_contract_hr_expense.egg-info/PKG-INFO
openerp_analytic_contract_hr_expense.egg-info/SOURCES.txt
openerp_analytic_contract_hr_expense.egg-info/dependency_links.txt
openerp_analytic_contract_hr_expense.egg-info/requires.txt
openerp_analytic_contract_hr_expense.egg-info/top_level.txt